evpn_ninja/__init__.py
evpn_ninja/__main__.py
evpn_ninja/cli.py
evpn_ninja/config.py
evpn_ninja/interactive.py
evpn_ninja/output.py
evpn_ninja/py.typed
evpn_ninja/validators.py
evpn_ninja/calculators/__init__.py
evpn_ninja/calculators/bandwidth.py
evpn_ninja/calculators/ebgp.py
evpn_ninja/calculators/evpn.py
evpn_ninja/calculators/fabric.py
evpn_ninja/calculators/mtu.py
evpn_ninja/calculators/multicast.py
evpn_ninja/calculators/multihoming.py
evpn_ninja/calculators/route_reflector.py
evpn_ninja/calculators/topology.py
evpn_ninja/calculators/vni.py
evpn_ninja/exporters/__init__.py
evpn_ninja/exporters/ansible.py
evpn_ninja/exporters/containerlab.py
evpn_ninja/exporters/eve_gns3.py
evpn_ninja/exporters/nornir.py
evpn_ninja-1.0.1.dist-info/licenses/LICENSE
evpn_ninja-1.0.1.dist-info/METADATA
evpn_ninja-1.0.1.dist-info/WHEEL
evpn_ninja-1.0.1.dist-info/entry_points.txt
evpn_ninja-1.0.1.dist-info/top_level.txt
evpn_ninja-1.0.1.dist-info/RECORD
