Metadata-Version: 2.4
Name: evpn-ninja
Version: 1.0.1
Summary: EVPN Ninja - VXLAN/EVPN fabric calculator for VNI allocation, fabric planning, EVPN parameters, MTU calculation
Author-email: Berik Ashimov <berik@ashimov.com>
Maintainer-email: Berik Ashimov <berik@ashimov.com>
License: MIT
Project-URL: Homepage, https://github.com/ashimov/evpn-ninja
Project-URL: Documentation, https://github.com/ashimov/evpn-ninja#readme
Project-URL: Repository, https://github.com/ashimov/evpn-ninja.git
Project-URL: Issues, https://github.com/ashimov/evpn-ninja/issues
Project-URL: Changelog, https://github.com/ashimov/evpn-ninja/blob/main/CHANGELOG.md
Keywords: vxlan,evpn,bgp,network,datacenter,fabric,calculator,cli,automation,cisco,arista,juniper
Classifier: Development Status :: 4 - Beta
Classifier: Environment :: Console
Classifier: Intended Audience :: System Administrators
Classifier: Intended Audience :: Telecommunications Industry
Classifier: Intended Audience :: Information Technology
Classifier: License :: OSI Approved :: MIT License
Classifier: Operating System :: OS Independent
Classifier: Programming Language :: Python :: 3
Classifier: Programming Language :: Python :: 3.10
Classifier: Programming Language :: Python :: 3.11
Classifier: Programming Language :: Python :: 3.12
Classifier: Programming Language :: Python :: 3.13
Classifier: Topic :: System :: Networking
Classifier: Topic :: Utilities
Classifier: Typing :: Typed
Requires-Python: >=3.10
License-File: LICENSE
Requires-Dist: typer>=0.9.0
Requires-Dist: rich>=13.0.0
Requires-Dist: questionary>=2.0.0
Requires-Dist: pyyaml>=6.0
Provides-Extra: dev
Requires-Dist: pytest>=7.0.0; extra == "dev"
Requires-Dist: pytest-cov>=4.0.0; extra == "dev"
Requires-Dist: ruff>=0.1.0; extra == "dev"
Requires-Dist: mypy>=1.0.0; extra == "dev"
Requires-Dist: types-PyYAML>=6.0.0; extra == "dev"
Requires-Dist: pre-commit>=3.0.0; extra == "dev"
Provides-Extra: build
Requires-Dist: pyinstaller>=6.0.0; extra == "build"
Dynamic: license-file
